nicegui_g6/__init__.py
nicegui_g6/core/g6.js
nicegui_g6/core/g6.py
nicegui_g6/version.py
nicegui_g6-0.1.1.dist-info/LICENSE
nicegui_g6-0.1.1.dist-info/METADATA
nicegui_g6-0.1.1.dist-info/WHEEL
nicegui_g6-0.1.1.dist-info/RECORD
