Metadata-Version: 2.1
Name: nicegui-g6
Version: 0.1.1
Summary: A component of AntV G6 visualization engine implemented based on NiceGUI
License: MIT
Author: CrystalWindSnake
Author-email: 568166495@qq.com
Requires-Python: >=3.8,<4.0
Classifier: License :: OSI Approved :: MIT License
Classifier: Programming Language :: Python :: 3
Classifier: Programming Language :: Python :: 3.8
Classifier: Programming Language :: Python :: 3.9
Classifier: Programming Language :: Python :: 3.10
Classifier: Programming Language :: Python :: 3.11
Classifier: Programming Language :: Python :: 3.12
Requires-Dist: nicegui (>=1.4.22,<2.0.0)
